uniqed/__init__.py
uniqed/__pycache__/__init__.cpython-38.pyc
uniqed/data/__init__.py
uniqed/data/gen_logmap.py
uniqed/data/__pycache__/__init__.cpython-38.pyc
uniqed/data/__pycache__/gen_logmap.cpython-38.pyc
uniqed/models/__init__.py
uniqed/models/tof.py
uniqed/models/__pycache__/__init__.cpython-38.pyc
uniqed/models/__pycache__/tof.cpython-38.pyc
uniqed/runners/__init__.py
uniqed/runners/tof_run.py
uniqed/runners/__pycache__/__init__.cpython-38.pyc
uniqed/runners/__pycache__/tof_run.cpython-38.pyc
uniqed/transformers/__init__.py
uniqed/transformers/transformers.py
uniqed/transformers/__pycache__/__init__.cpython-38.pyc
uniqed/transformers/__pycache__/transformers.cpython-38.pyc
uniqed-0.0.2.dist-info/LICENSE.txt
uniqed-0.0.2.dist-info/METADATA
uniqed-0.0.2.dist-info/WHEEL
uniqed-0.0.2.dist-info/top_level.txt
uniqed-0.0.2.dist-info/RECORD
