Metadata-Version: 2.1
Name: uniqed
Version: 0.0.2
Summary: Simple implementation of the Temporal Outlier Factor
Home-page: UNKNOWN
Author: Zsigmond Benko, Tamas Babel, Zoltan Somogyvari
Author-email: benko.zsigmond@gmail.com
License: Simplified BSD
Platform: UNKNOWN
Classifier: Intended Audience :: Science/Research
Classifier: Topic :: Scientific/Engineering :: Mathematics
Classifier: Topic :: Scientific/Engineering :: Medical Science Apps.
Classifier: Topic :: Scientific/Engineering :: Physics
Classifier: Topic :: Scientific/Engineering :: Astronomy
Requires-Dist: numpy
Requires-Dist: scipy
Requires-Dist: scikit-learn
Requires-Dist: pandas
Requires-Dist: matplotlib
